LICENSE.txt
MANIFEST.in
README.md
setup.cfg
setup.py
livestream_monitor_classifier/__init__.py
livestream_monitor_classifier/main.py
livestream_monitor_classifier.egg-info/PKG-INFO
livestream_monitor_classifier.egg-info/SOURCES.txt
livestream_monitor_classifier.egg-info/dependency_links.txt
livestream_monitor_classifier.egg-info/requires.txt
livestream_monitor_classifier.egg-info/top_level.txt
livestream_monitor_classifier/__pycache__/__init__.cpython-310.pyc
livestream_monitor_classifier/__pycache__/main.cpython-310.pyc
livestream_monitor_classifier/data/stopwords-custom.txt
livestream_monitor_classifier/helper/__init__.py
livestream_monitor_classifier/helper/preprocess.py
livestream_monitor_classifier/helper/__pycache__/__init__.cpython-310.pyc
livestream_monitor_classifier/helper/__pycache__/preprocess.cpython-310.pyc
livestream_monitor_classifier/model/sklearn_MNB.model