Metadata-Version: 2.1
Name: livestream-monitor-classifier
Version: 0.0.4
Summary: A Machine Learning Classifier that used to for my personal thesis project called livestream monitor
Home-page: https://github.com/rfirmansyh/livestream_monitor_classifier
Download-URL: https://github.com/rfirmansyh/livestream_monitor_classifier/archive/refs/tags/v0.0.4.tar.gz
Author: Rahmad Firmansyah
Author-email: rahmadfirmansyah.id@gmail.com
License: MIT
Keywords: rfirmansyh,livestream_monitor_classifier
Classifier: Development Status :: 3 - Alpha
Classifier: Intended Audience :: Developers
Classifier: Topic :: Software Development :: Build Tools
Classifier: License :: OSI Approved :: MIT License
Classifier: Programming Language :: Python :: 3
Classifier: Programming Language :: Python :: 3.9
Classifier: Programming Language :: Python :: 3.10
License-File: LICENSE.txt
